httpie_keystone_auth.py
httpie_keystone_auth-0.3.1.dist-info/LICENSE
httpie_keystone_auth-0.3.1.dist-info/METADATA
httpie_keystone_auth-0.3.1.dist-info/WHEEL
httpie_keystone_auth-0.3.1.dist-info/entry_points.txt
httpie_keystone_auth-0.3.1.dist-info/top_level.txt
httpie_keystone_auth-0.3.1.dist-info/RECORD
