Metadata-Version: 2.1
Name: httpie-keystone-auth
Version: 0.3.1
Summary: OpenStack Keystone auth plugin for HTTPie
Home-page: https://github.com/pshchelo/httpie-keystone-auth
Download-URL: https://github.com/pshchelo/httpie-keystone-auth
Author-email: Pavlo Shchelokovskyy <shchelokovskyy@gmail.com>
License: MIT
Classifier: Development Status :: 4 - Beta
Classifier: Programming Language :: Python
Classifier: Programming Language :: Python :: 3 :: Only
Classifier: Environment :: Plugins
Classifier: License :: OSI Approved :: MIT License
Classifier: Topic :: Internet :: WWW/HTTP
Classifier: Topic :: Utilities
Requires-Python: >=3.7
License-File: LICENSE
Requires-Dist: httpie >=3.0.0
Requires-Dist: openstacksdk >=0.59.0
Requires-Dist: os-service-types >=1.7.0
